{
  "indexes": [
    {
      "collectionGroup": "cards",
      "queryScope": "COLLECTION",
      "fields": [
        {
          "fieldPath": "activa",
          "order": "ASCENDING"
        },
        {
          "fieldPath": "createdAt",
          "order": "DESCENDING"
        },
        {
          "fieldPath": "__name__",
          "order": "DESCENDING"
        }
      ],
      "density": "SPARSE_ALL"
    },
    {
      "collectionGroup": "expenses",
      "queryScope": "COLLECTION",
      "fields": [
        {
          "fieldPath": "monthKey",
          "order": "ASCENDING"
        },
        {
          "fieldPath": "fecha",
          "order": "DESCENDING"
        },
        {
          "fieldPath": "__name__",
          "order": "DESCENDING"
        }
      ],
      "density": "SPARSE_ALL"
    }
  ],
  "fieldOverrides": []
}